{
    "displayField": "title",
    "name": "Meta Data",
    "description": "Add custom page meta data values.",
    "fields": [
        {
            "id": "title",
            "name": "Title",
            "type": "Symbol",
            "localized": false,
            "required": false,
            "validations": [],
            "disabled": false,
            "omitted": false
        },
        {
            "id": "description",
            "name": "Description",
            "type": "Text",
            "localized": false,
            "required": false,
            "validations": [],
            "disabled": false,
            "omitted": false
        },
        {
            "id": "keywords",
            "name": "Keywords",
            "type": "Array",
            "localized": false,
            "required": false,
            "validations": [],
            "disabled": false,
            "omitted": false,
            "items": {
                "type": "Symbol",
                "validations": []
            }
        },
        {
            "id": "image",
            "name": "Image",
            "type": "Link",
            "localized": false,
            "required": false,
            "validations": [],
            "disabled": false,
            "omitted": false,
            "linkType": "Asset"
        }
    ],
    "sys": {
        "id": "metaData"
    }
}